yahoo_search_api_v12/__init__.py
yahoo_search_api_v12/api_client.py
yahoo_search_api_v12/configuration.py
yahoo_search_api_v12/exceptions.py
yahoo_search_api_v12/rest.py
yahoo_search_api_v12/api/__init__.py
yahoo_search_api_v12/api/account_customizer_service_api.py
yahoo_search_api_v12/api/account_link_service_api.py
yahoo_search_api_v12/api/account_management_service_api.py
yahoo_search_api_v12/api/account_service_api.py
yahoo_search_api_v12/api/account_shared_service_api.py
yahoo_search_api_v12/api/account_tracking_url_service_api.py
yahoo_search_api_v12/api/ad_group_ad_label_service_api.py
yahoo_search_api_v12/api/ad_group_ad_service_api.py
yahoo_search_api_v12/api/ad_group_asset_service_api.py
yahoo_search_api_v12/api/ad_group_bid_multiplier_service_api.py
yahoo_search_api_v12/api/ad_group_criterion_customizer_service_api.py
yahoo_search_api_v12/api/ad_group_criterion_label_service_api.py
yahoo_search_api_v12/api/ad_group_criterion_service_api.py
yahoo_search_api_v12/api/ad_group_customizer_service_api.py
yahoo_search_api_v12/api/ad_group_label_service_api.py
yahoo_search_api_v12/api/ad_group_retargeting_list_service_api.py
yahoo_search_api_v12/api/ad_group_service_api.py
yahoo_search_api_v12/api/ad_group_webpage_service_api.py
yahoo_search_api_v12/api/app_link_service_api.py
yahoo_search_api_v12/api/asset_service_api.py
yahoo_search_api_v12/api/audit_log_service_api.py
yahoo_search_api_v12/api/balance_service_api.py
yahoo_search_api_v12/api/base_account_service_api.py
yahoo_search_api_v12/api/bidding_seasonality_adjustment_service_api.py
yahoo_search_api_v12/api/bidding_strategy_service_api.py
yahoo_search_api_v12/api/budget_order_service_api.py
yahoo_search_api_v12/api/campaign_asset_service_api.py
yahoo_search_api_v12/api/campaign_budget_service_api.py
yahoo_search_api_v12/api/campaign_criterion_service_api.py
yahoo_search_api_v12/api/campaign_customizer_service_api.py
yahoo_search_api_v12/api/campaign_export_service_api.py
yahoo_search_api_v12-1.0.0.dist-info/METADATA
yahoo_search_api_v12-1.0.0.dist-info/WHEEL
yahoo_search_api_v12-1.0.0.dist-info/top_level.txt
yahoo_search_api_v12-1.0.0.dist-info/RECORD
